api/__init__.py
api/urls.py
functions/__init__.py
functions/cluster_functions.py
functions/data_analysis_functions.py
functions/db_functions.py
functions/docking_functions.py
functions/misc_functions.py
functions/pandda_functions.py
functions/proasis_api_funcs.py
luigi_classes/__init__.py
luigi_classes/check_nudt5.py
luigi_classes/cluster_submission.py
luigi_classes/config_classes.py
luigi_classes/hotspot_maps.py
luigi_classes/html_generators.py
luigi_classes/ligand_analysis.py
luigi_classes/post_dock.py
luigi_classes/prepare_dock.py
luigi_classes/prepare_maps.py
luigi_classes/pull_proasis.py
luigi_classes/run_dock.py
luigi_classes/transfer_pandda.py
luigi_classes/transfer_proasis.py
luigi_classes/transfer_soakdb.py
luigi_classes/transfer_verne.py
overview/__init__.py
overview/urls.py
overview/views.py
overview/templates/__init__.py
overview/templates/overview/__init__.py
xchem_db/__init__.py
xchem_db/apps.py
xchem_db/models.py
xchem_db/routers.py
xchem_db/serializers.py
xchem_db/tests.py
xchem_db/views.py
xchem_db-0.1.26b0.dist-info/LICENSE
xchem_db-0.1.26b0.dist-info/METADATA
xchem_db-0.1.26b0.dist-info/WHEEL
xchem_db-0.1.26b0.dist-info/entry_points.txt
xchem_db-0.1.26b0.dist-info/top_level.txt
xchem_db-0.1.26b0.dist-info/RECORD
